VOLT/__init__.py
VOLT/get_chars.py
VOLT/get_tokens.py
VOLT/volt.py
VOLT/tests/__init__.py
VOLT/tests/test_volt.py
VLOT-0.1.0.dist-info/METADATA
VLOT-0.1.0.dist-info/WHEEL
VLOT-0.1.0.dist-info/top_level.txt
VLOT-0.1.0.dist-info/RECORD
